mock_server/__init__.py
mock_server/__init__.pyc
mock_server/api.py
mock_server/api_settings.py
mock_server/application.py
mock_server/data.py
mock_server/fastrpcapi.py
mock_server/handlers.py
mock_server/jsonrpc.py
mock_server/methodslisting.py
mock_server/model.py
mock_server/ordereddict.py
mock_server/rest.py
mock_server/rpc.py
mock_server/text.py
mock_server/tornado_flash_message_mixin.py
mock_server/tornado_http_auth_basic_mixin.py
mock_server/util.py
mock_server/validators.py
mock_server/xmlrpc.py
mock_server/example/application.json
mock_server/example/RPC2/user.list
mock_server/example/event/POST_200.json
mock_server/example/event/POST_H_200.json
mock_server/example/event/POST_doc.md
mock_server/example/products/__id/GET_200.json
mock_server/example/products/__id/GET_H_200.json
mock_server/example/products/__id/GET_doc.md
mock_server/example/user/GET_200.json
mock_server/example/user/GET_H_200.json
mock_server/example/user/GET_doc.md
mock_server/example/user/POST_200.json
mock_server/example/user/POST_H_200.json
mock_server/example/user/__id/GET_200.json
mock_server/example/user/__id/GET_H_200.json
mock_server/example/user/__id/family/__name/GET_200.json
mock_server/example/user/__id/family/__name/GET_H_200.json
mock_server/example/user/john/GET_200.json
mock_server/example/user/john/GET_H_200.json
mock_server/example/user/kevin/DELETE_404.json
mock_server/example/user/kevin/DELETE_H_404.json
mock_server/example/user/tom/GET_200.json
mock_server/example/user/tom/GET_200.xml
mock_server/example/user/tom/GET_H_200.json
mock_server/example/user/tom/GET_H_200.xml
mock_server/static/css/login.css
mock_server/static/css/main.css
mock_server/static/img/favicon.ico
mock_server/static/js/create-resource.js
mock_server/static/js/create-rest.js
mock_server/static/js/list-resources.js
mock_server/static/js/util.js
mock_server/static/vendor/ace/js/ace.js
mock_server/static/vendor/ace/js/mode-html.js
mock_server-0.3.9.dist-info/METADATA
mock_server-0.3.9.dist-info/RECORD
mock_server-0.3.9.dist-info/WHEEL
mock_server-0.3.9.dist-info/top_level.txt
