Metadata-Version: 2.1
Name: mock-server
Version: 0.3.9
Summary: Simple mock server for REST API
Home-page: https://github.com/tomashanacek/mock-server
Author: Tomas Hanacek
Author-email: tomas.hanacek1@gmail.com
License: http://www.apache.org/licenses/LICENSE-2.0
Platform: UNKNOWN
Classifier: Programming Language :: Python
Classifier: License :: OSI Approved :: Apache Software License
Classifier: Intended Audience :: Developers
Classifier: Topic :: Internet
Classifier: Topic :: Software Development :: Documentation
Requires-Dist: tornado (==4.3)
Requires-Dist: markdown2 (>=2.1.0)
Requires-Dist: py-bcrypt (>=0.3)
Requires-Dist: futures (>=2.1.3)
Requires-Dist: jsonrpclib (==0.1.7)
Requires-Dist: six (==1.10.0)
